MANIFEST.in
README.md
setup.py
a8/__init__.py
a8/__main__.py
a8/a8_example_ext.py
a8/actions.py
a8/app.py
a8/bookmarks.py
a8/buffers.py
a8/bus.py
a8/config.py
a8/contexts.py
a8/extensions.py
a8/files.py
a8/lists.py
a8/resources.py
a8/sessions.py
a8/shortcuts.py
a8/terminals.py
a8/version.py
a8/vimembed.py
a8/window.py
a8.egg-info/PKG-INFO
a8.egg-info/SOURCES.txt
a8.egg-info/dependency_links.txt
a8.egg-info/entry_points.txt
a8.egg-info/not-zip-safe
a8.egg-info/requires.txt
a8.egg-info/top_level.txt
a8/data/a8.vim
a8/data/icons/a8.png
a8/data/icons/application_delete.png
a8/data/icons/application_lightning.png
a8/data/icons/application_xp_terminal.png
a8/data/icons/arrow_refresh_small.png
a8/data/icons/asterisk_orange.png
a8/data/icons/asterisk_yellow.png
a8/data/icons/car.png
a8/data/icons/cog.png
a8/data/icons/cross.png
a8/data/icons/delete.png
a8/data/icons/find.png
a8/data/icons/folder.png
a8/data/icons/house_go.png
a8/data/icons/lorry.png
a8/data/icons/page_white.png
a8/data/icons/page_white_copy.png
a8/data/icons/page_white_stack.png
a8/data/icons/page_white_visualstudio.png
a8/data/icons/page_world.png
a8/data/icons/paste_plain.png
a8/data/icons/resultset_next.png
a8/data/icons/resultset_previous.png
a8/data/icons/script_lightning.png
a8/data/icons/star.png
a8/data/icons/terminal_pop_in.png
a8/data/icons/terminal_pop_out.png
a8/data/icons/textfield_add.png
a8/data/icons/textfield_delete.png
a8/data/icons/tick.png
a8/data/icons/world_go.png