Metadata-Version: 1.0
Name: a8
Version: 1.0
Summary: The Abominade IDE
Home-page: http://abominade.org
Author: Ali Afshar
Author-email: aafshar@gmail.com
License: GPL
Platform: UNKNOWN
